{"google":[{"title":"Saturday links: learn or die","publication_date":"2016-10-15 14:56:32 +0000","url":"http://finance.yahoo.com/tumblr/blog-saturday-links-learn-or-die-145637050.html","summary":"Saturday links: learn or die"},{"title":"3 Top Driverless Car Stocks to Buy Now","publication_date":"2016-10-15 13:01:20 +0000","url":"http://www.fool.com/investing/2016/10/15/3-top-driverless-car-stocks-to-buy-now.aspx?source=yahoo-2&utm_campaign=article&utm_medium=feed&utm_source=yahoo-2","summary":"3 Top Driverless Car Stocks to Buy Now"},{"title":"Apple, Google Product Leaks Proliferate, But Don't Tell Whole Story","publication_date":"2016-10-15 12:30:24 +0000","url":"http://www.investors.com/news/technology/apple-google-product-leaks-dont-tell-the-whole-story/","summary":"Apple, Google Product Leaks Proliferate, But Don't Tell Whole Story"}]}